<?xml version="1.0" encoding="UTF-8"?>
<gresources>
  <gresource prefix="/com/usebottles/bottles">
    <file>style.css</file>
    <file>yaru.css</file>
    <file>window.ui</file>
    <file>empty.ui</file>
    <file>new.ui</file>
    <file>list.ui</file>
    <file>list-entry.ui</file>
    <file>details.ui</file>
    <file>preferences.ui</file>
    <file>download-entry.ui</file>
    <file>runner-entry.ui</file>
    <file>dxvk-entry.ui</file>
    <file>dependency-entry.ui</file>
    <file>program-entry.ui</file>
    <file>task-manager.ui</file>
    <file>importer.ui</file>
    <file>importer-entry.ui</file>
    <file>state-entry.ui</file>
    <file>installer-entry.ui</file>
    <file>environment-entry.ui</file>
    <file>dialog-launch-options.ui</file>
    <file>dialog-dll-overrides.ui</file>
    <file>dialog-environment-variables.ui</file>
    <file>dll-override-entry.ui</file>
    <file>onboard.ui</file>
    <file>about.ui</file>
  </gresource>
</gresources>
